django_sgapi-1.0.0.dist-info/DESCRIPTION.rst
django_sgapi-1.0.0.dist-info/METADATA
django_sgapi-1.0.0.dist-info/RECORD
django_sgapi-1.0.0.dist-info/WHEEL
django_sgapi-1.0.0.dist-info/metadata.json
django_sgapi-1.0.0.dist-info/top_level.txt
sgbackend/__init__.py
sgbackend/mail.py
sgbackend/version.py
